jvdeploy/Dockerfile.base
jvdeploy/__init__.py
jvdeploy/bundler.py
jvdeploy/cli.py
jvdeploy/config.py
jvdeploy/docker_builder.py
jvdeploy/dockerfile_generator.py
jvdeploy/aws/__init__.py
jvdeploy/aws/lambda_deployer.py
jvdeploy/templates/deploy.yaml.template
jvdeploy-0.1.0.dist-info/licenses/LICENSE
jvdeploy-0.1.0.dist-info/METADATA
jvdeploy-0.1.0.dist-info/WHEEL
jvdeploy-0.1.0.dist-info/entry_points.txt
jvdeploy-0.1.0.dist-info/top_level.txt
jvdeploy-0.1.0.dist-info/RECORD
