Metadata-Version: 2.4
Name: jvdeploy
Version: 0.1.0
Summary: Dockerfile generator for jvagent applications
Home-page: https://github.com/your-org/jvdeploy
Author: TrueSelph Inc.
Author-email: "TrueSelph Inc." <adminh@trueselph.com>
License: MIT
Project-URL: Homepage, https://github.com/your-org/jvdeploy
Project-URL: Repository, https://github.com/your-org/jvdeploy
Project-URL: Issues, https://github.com/your-org/jvdeploy/issues
Keywords: docker,dockerfile,bundler,jvagent,deployment
Classifier: Development Status :: 3 - Alpha
Classifier: Intended Audience :: Developers
Classifier: License :: OSI Approved :: MIT License
Classifier: Programming Language :: Python :: 3.8
Classifier: Programming Language :: Python :: 3.9
Classifier: Programming Language :: Python :: 3.10
Classifier: Programming Language :: Python :: 3.11
Classifier: Programming Language :: Python :: 3.12
Classifier: Topic :: Software Development :: Libraries :: Python Modules
Classifier: Topic :: Software Development :: Build Tools
Requires-Python: >=3.8
License-File: LICENSE
Requires-Dist: pyyaml>=6.0.0
Provides-Extra: deploy
Requires-Dist: boto3>=1.28.0; extra == "deploy"
Requires-Dist: jinja2>=3.1.0; extra == "deploy"
Provides-Extra: dev
Requires-Dist: pytest>=7.0; extra == "dev"
Requires-Dist: black>=23.9.0; extra == "dev"
Requires-Dist: ruff>=0.1.0; extra == "dev"
Requires-Dist: mypy>=1.6.0; extra == "dev"
Requires-Dist: boto3>=1.28.0; extra == "dev"
Requires-Dist: jinja2>=3.1.0; extra == "dev"
Provides-Extra: test
Requires-Dist: pytest>=7.0; extra == "test"
Dynamic: author
Dynamic: home-page
Dynamic: license-file
Dynamic: requires-python
